markdown_tree_parser/__init__.py
markdown_tree_parser/parser.py
tests/__init__.py
tests/art_tests.py
tests/file_tests.py
markdown_tree_parser-0.1.dist-info/LICENSE
markdown_tree_parser-0.1.dist-info/METADATA
markdown_tree_parser-0.1.dist-info/WHEEL
markdown_tree_parser-0.1.dist-info/top_level.txt
markdown_tree_parser-0.1.dist-info/RECORD
