Metadata-Version: 2.1
Name: markdown-tree-parser
Version: 0.1
Summary: Markdown tree parser
Home-page: https://github.com/phpusr/markdown-tree-parser
Author: phpusr
Author-email: phpusr@gmail.com
License: UNKNOWN
Platform: UNKNOWN
Classifier: Programming Language :: Python :: 3
Classifier: License :: OSI Approved :: MIT License
Classifier: Operating System :: OS Independent
Requires-Python: >=3.6
